[{"PackageId":32,"PackageName":"Attended Check-in","VersionId":322,"VersionLabel":"1.7","VendorId":3724,"VendorName":"Kingdom First Solutions Inc (KFS)","InstalledBy":"Kenny Snow","InstallDateTime":"2019-09-04T10:40:30.5322887"},{"PackageId":74,"PackageName":"Acme Certificate","VersionId":203,"VersionLabel":"2.0.0","VendorId":33866,"VendorName":"Blue Box Moon","InstalledBy":"Jon Woodson","InstallDateTime":"2018-10-15T08:53:30.5957309"},{"PackageId":84,"PackageName":"Pastoral Care","VersionId":265,"VersionLabel":"3","VendorId":92,"VendorName":"Southeast Christian Church","InstalledBy":"Jon Woodson","InstallDateTime":"2019-05-10T09:44:40.3588452"},{"PackageId":92,"PackageName":"Signup Wizard","VersionId":327,"VersionLabel":"1.3","VendorId":92,"VendorName":"Southeast Christian Church","InstalledBy":"Kenny Snow","InstallDateTime":"2019-03-06T08:27:00.0568469"},{"PackageId":49,"PackageName":"SQL Map","VersionId":109,"VersionLabel":"1.0","VendorId":1146,"VendorName":"Christ's Church of Flagstaff","InstalledBy":"Kenny Snow","InstallDateTime":"2018-10-16T10:34:58.2036953"},{"PackageId":53,"PackageName":"Group Type Change Tool","VersionId":122,"VersionLabel":"1.0","VendorId":92,"VendorName":"Southeast Christian Church","InstalledBy":"Kenny Snow","InstallDateTime":"2018-10-16T10:35:28.0128758"},{"PackageId":69,"PackageName":"Rock Shop Notifications","VersionId":201,"VersionLabel":"2.0.0","VendorId":1278,"VendorName":"Shepherd Church","InstalledBy":"Kenny Snow","InstallDateTime":"2018-10-16T10:57:31.8053286"},{"PackageId":22,"PackageName":"Lava Tester","VersionId":248,"VersionLabel":"1.6.0","VendorId":69,"VendorName":"Central Christian Church (AZ)","InstalledBy":"Matt Floyd","InstallDateTime":"2018-10-19T14:08:49.9736865"},{"PackageId":82,"PackageName":"Font Awesome Icon Seek and Find","VersionId":193,"VersionLabel":"1.0","VendorId":15838,"VendorName":"Covenant United Methodist Church","InstalledBy":"Kenny Snow","InstallDateTime":"2018-10-22T09:22:32.4187574"},{"PackageId":85,"PackageName":"Workflow Launcher","VersionId":328,"VersionLabel":"1.2","VendorId":92,"VendorName":"Southeast Christian Church","InstalledBy":"Kenny Snow","InstallDateTime":"2019-03-06T08:27:27.3069687"},{"PackageId":33,"PackageName":"Check-in Tools","VersionId":61,"VersionLabel":"1.5.0","VendorId":69,"VendorName":"Central Christian Church (AZ)","InstalledBy":"Kenny Snow","InstallDateTime":"2018-12-02T07:58:36.8719808"},{"PackageId":81,"PackageName":"Open Connections Digest","VersionId":245,"VersionLabel":"2.0","VendorId":7157,"VendorName":"BEMA Information Technologies","InstalledBy":"Kenny Snow","InstallDateTime":"2018-12-02T07:59:33.4284684"},{"PackageId":6,"PackageName":"Azure Storage Provider","VersionId":347,"VersionLabel":"Version 1.4","VendorId":7689,"VendorName":"Pillars","InstalledBy":"Jon Woodson","InstallDateTime":"2019-05-07T13:36:53.2328633"},{"PackageId":34,"PackageName":"Cloudinary Storage Provider","VersionId":253,"VersionLabel":"v2.1","VendorId":70,"VendorName":"Mine Cart Studio","InstalledBy":"Jon Woodson","InstallDateTime":"2019-01-14T10:13:59.1622049"},{"PackageId":87,"PackageName":"Storage Mover","VersionId":267,"VersionLabel":"v1.1","VendorId":70,"VendorName":"Mine Cart Studio","InstalledBy":"Jon Woodson","InstallDateTime":"2019-01-14T10:36:18.1411057"},{"PackageId":86,"PackageName":"Agency Theme","VersionId":225,"VersionLabel":"1.1","VendorId":7157,"VendorName":"BEMA Information Technologies","InstalledBy":"Jon Woodson","InstallDateTime":"2019-01-30T12:51:36.7679987"},{"PackageId":55,"PackageName":"CSV People Importer","VersionId":222,"VersionLabel":"2.1","VendorId":3764,"VendorName":"Lanio","InstalledBy":"Jon Woodson","InstallDateTime":"2019-06-21T11:07:11.7594647"},{"PackageId":101,"PackageName":"Advanced Person Attributes Form","VersionId":387,"VersionLabel":"2.1","VendorId":3724,"VendorName":"Kingdom First Solutions Inc (KFS)","InstalledBy":"Kenny Snow","InstallDateTime":"2019-09-10T08:12:12.4750406"},{"PackageId":114,"PackageName":"Watchdog Monitor","VersionId":397,"VersionLabel":"1.0.1","VendorId":33866,"VendorName":"Blue Box Moon","InstalledBy":"Kenny Snow","InstallDateTime":"2019-10-24T11:24:34.5454187"},{"PackageId":68,"PackageName":"Workflow Stimpack","VersionId":382,"VersionLabel":"2.0.0","VendorId":33866,"VendorName":"Blue Box Moon","InstalledBy":"Kenny Snow","InstallDateTime":"2019-09-10T08:14:47.7342306"},{"PackageId":109,"PackageName":"Workflow Extensions","VersionId":363,"VersionLabel":"1.0.2.4","VendorId":7157,"VendorName":"BEMA Information Technologies","InstalledBy":"Jon Woodson","InstallDateTime":"2019-08-20T20:16:26.1437825"},{"PackageId":105,"PackageName":"Advanced Check-In Monitor","VersionId":378,"VersionLabel":"2.0","VendorId":3724,"VendorName":"Kingdom First Solutions Inc (KFS)","InstalledBy":"Kenny Snow","InstallDateTime":"2019-09-04T10:42:55.8066158"},{"PackageId":115,"PackageName":"BEMA Ministry Safe Integration","VersionId":359,"VersionLabel":"1.0.0.2","VendorId":7157,"VendorName":"BEMA Information Technologies","InstalledBy":"Kenny Snow","InstallDateTime":"2019-10-24T11:20:53.6226806"},{"PackageId":89,"PackageName":"RockPress","VersionId":242,"VersionLabel":"1.0","VendorId":41380,"VendorName":"FireTree Design","InstalledBy":"Jon Woodson","InstallDateTime":"2019-11-19T15:18:45.5861152"},{"PackageId":25,"PackageName":"Birthday Announcements","VersionId":33,"VersionLabel":"v1.0","VendorId":70,"VendorName":"Mine Cart Studio","InstalledBy":"Jon Woodson","InstallDateTime":"2019-12-16T09:09:23.3358435"},{"PackageId":65,"PackageName":"Lava Additions","VersionId":157,"VersionLabel":"1.1.0","VendorId":33866,"VendorName":"Blue Box Moon","InstalledBy":"Jon Woodson","InstallDateTime":"2020-02-11T12:34:40.2598138"},{"PackageId":129,"PackageName":"Connection Campaigns","VersionId":465,"VersionLabel":"v1.2","VendorId":65,"VendorName":"Spark Development Network","InstalledBy":"Jon Woodson","InstallDateTime":"2020-04-07T12:05:02.570481"}]